pelicun/__init__.py
pelicun/assessment.py
pelicun/auto.py
pelicun/base.py
pelicun/db.py
pelicun/file_io.py
pelicun/model.py
pelicun/post_install.py
pelicun/uq.py
pelicun/settings/default_config.json
pelicun/settings/default_units.json
pelicun/tools/DL_calculation.py
pelicun/tools/HDF_to_CSV.py
pelicun/tools/export_DB.py
pelicun_test20230830-3.2b4.dist-info/LICENSE
pelicun_test20230830-3.2b4.dist-info/METADATA
pelicun_test20230830-3.2b4.dist-info/WHEEL
pelicun_test20230830-3.2b4.dist-info/top_level.txt
pelicun_test20230830-3.2b4.dist-info/RECORD
