Metadata-Version: 2.1
Name: pelicun-test20230830
Version: 3.2b4
Summary: Probabilistic Estimation of Losses, Injuries, and Community resilience Under Natural hazard events
Home-page: http://nheri-simcenter.github.io/pelicun/
Author: Adam Zsarnóczay
Author-email: adamzs@stanford.edu
License: BSD License
Platform: any
Classifier: Programming Language :: Python
Classifier: Development Status :: 5 - Production/Stable
Classifier: Natural Language :: English
Classifier: Environment :: Console
Classifier: Framework :: Jupyter
Classifier: Intended Audience :: Education
Classifier: Intended Audience :: Science/Research
Classifier: License :: OSI Approved :: BSD License
Classifier: Natural Language :: English
Classifier: Operating System :: Microsoft :: Windows
Classifier: Operating System :: MacOS :: MacOS X
Classifier: Operating System :: Unix
Classifier: Programming Language :: Python :: 3.8
Classifier: Programming Language :: Python :: 3.9
Classifier: Programming Language :: Python :: 3.10
Classifier: Topic :: Scientific/Engineering
License-File: LICENSE
Requires-Dist: numpy <2.0,>=1.22.0
Requires-Dist: scipy <2.0,>=1.7.0
Requires-Dist: pandas <2.0,>=1.4.0
Requires-Dist: tables >=3.7.0
Requires-Dist: requests >=2.0.0
Provides-Extra: testing
Requires-Dist: pytest ; extra == 'testing'
